pyhula/__init__.py
pyhula/userapi.py
pyhula/f09-lite-trans/avcodec-58.dll
pyhula/f09-lite-trans/avdevice-58.dll
pyhula/f09-lite-trans/avfilter-7.dll
pyhula/f09-lite-trans/avformat-58.dll
pyhula/f09-lite-trans/avutil-56.dll
pyhula/f09-lite-trans/f09-ffmpeg-lib.dll
pyhula/f09-lite-trans/postproc-55.dll
pyhula/f09-lite-trans/swresample-3.dll
pyhula/f09-lite-trans/swscale-5.dll
pyhula/pypack/fylo/commandprocessor.cp36-win_amd64.pyd
pyhula/pypack/fylo/config.cp36-win_amd64.pyd
pyhula/pypack/fylo/controlserver.cp36-win_amd64.pyd
pyhula/pypack/fylo/mavanalyzer.cp36-win_amd64.pyd
pyhula/pypack/fylo/mavlink.cp36-win_amd64.pyd
pyhula/pypack/fylo/msganalyzer.cp36-win_amd64.pyd
pyhula/pypack/fylo/stateprocessor.cp36-win_amd64.pyd
pyhula/pypack/fylo/taskprocessor.cp36-win_amd64.pyd
pyhula/pypack/fylo/uwb.cp36-win_amd64.pyd
pyhula/pypack/system/buffer.cp36-win_amd64.pyd
pyhula/pypack/system/command.cp36-win_amd64.pyd
pyhula/pypack/system/communicationcontroller.cp36-win_amd64.pyd
pyhula/pypack/system/communicationcontrollerfactory.cp36-win_amd64.pyd
pyhula/pypack/system/dancecontroller.cp36-win_amd64.pyd
pyhula/pypack/system/dancefileanalyzer.cp36-win_amd64.pyd
pyhula/pypack/system/datacenter.cp36-win_amd64.pyd
pyhula/pypack/system/event.cp36-win_amd64.pyd
pyhula/pypack/system/mavcrc.cp36-win_amd64.pyd
pyhula/pypack/system/network.cp36-win_amd64.pyd
pyhula/pypack/system/networkcontroller.cp36-win_amd64.pyd
pyhula/pypack/system/serialcontroller.cp36-win_amd64.pyd
pyhula/pypack/system/state.cp36-win_amd64.pyd
pyhula/pypack/system/system.cp36-win_amd64.pyd
pyhula/pypack/system/taskcontroller.cp36-win_amd64.pyd
pyhula-1.1.4.data/data/Lib/site-packages/pyhula/pypack/log.ini
pyhula-1.1.4.data/data/Lib/site-packages/pyhula/pypack/version.ini
pyhula-1.1.4.dist-info/METADATA
pyhula-1.1.4.dist-info/WHEEL
pyhula-1.1.4.dist-info/top_level.txt
pyhula-1.1.4.dist-info/RECORD
