Metadata-Version: 2.1
Name: pyhula
Version: 1.1.4
Summary: Hula package
Home-page: UNKNOWN
Author: HighGreat
Author-email: highgreat@hg-fly.com
License: UNKNOWN
Platform: UNKNOWN
Classifier: Intended Audience :: Education
Classifier: Development Status :: 2 - Pre-Alpha
Classifier: Programming Language :: Python
Classifier: Programming Language :: Python :: 3
Classifier: Programming Language :: Python :: 3.6
Classifier: Programming Language :: Python :: 3.7
Classifier: Programming Language :: Python :: 3.8
Classifier: Programming Language :: Python :: 3.9
Classifier: Programming Language :: Python :: 3.10
Classifier: Programming Language :: Python :: 3 :: Only
Classifier: Operating System :: Microsoft :: Windows
Requires-Python: >=3.6
Requires-Dist: numpy (>=1.18.2)
Requires-Dist: psutil (>=5.9.7)
Requires-Dist: pymavlink (>=2.4.41)
Requires-Dist: opencv-python (>=4.3.0.38)
Provides-Extra: docs
Requires-Dist: sphinx (<4.0.0,>=3.0.0) ; extra == 'docs'
